xztrainer/__init__.py
xztrainer/auto_tracker_config.py
xztrainer/context.py
xztrainer/functional.py
xztrainer/logger.py
xztrainer/model.py
xztrainer/setup_helper.py
xztrainer/tensor_helper.py
xztrainer/trainable.py
xztrainer/trainer.py
xztrainer-1.2.1.dist-info/METADATA
xztrainer-1.2.1.dist-info/WHEEL
xztrainer-1.2.1.dist-info/RECORD
