Metadata-Version: 2.1
Name: xztrainer
Version: 1.2.1
Summary: A customizable training pipeline for PyTorch
License: MPL-2.0
Author: Maxim Afanasyev
Author-email: mr.applexz@gmail.com
Requires-Python: >=3.9
Classifier: License :: OSI Approved
Classifier: Programming Language :: Python :: 3
Classifier: Programming Language :: Python :: 3.9
Classifier: Programming Language :: Python :: 3.10
Classifier: Programming Language :: Python :: 3.11
Classifier: Programming Language :: Python :: 3.12
Provides-Extra: numpy
Provides-Extra: torch
Requires-Dist: accelerate (>=0.29.2) ; extra == "torch"
Requires-Dist: numpy (>=1.24.2) ; extra == "numpy"
Requires-Dist: torch (>=1.10.0) ; extra == "torch"
Requires-Dist: torchmetrics (>=1.3.0) ; extra == "torch"
Requires-Dist: tqdm (>=4.62.3)
